opcuaAutomation/__init__.py
opcuaAutomation/client_OPC_UA.py
opcuaAutomation/resultsObjects.py
opcuaAutomation/uaDataType.py
opcuaautomation-1.0.0.dist-info/licenses/LICENCE.md
opcuaautomation-1.0.0.dist-info/METADATA
opcuaautomation-1.0.0.dist-info/WHEEL
opcuaautomation-1.0.0.dist-info/top_level.txt
opcuaautomation-1.0.0.dist-info/RECORD
